<?xml version="1.0" encoding="UTF-8"?>
<config xmlns="http://www.knime.org/2008/09/XMLConfig" xmlns:xsi="http://www.w3.org/2001/XMLSchema-instance" xsi:schemaLocation="http://www.knime.org/2008/09/XMLConfig http://www.knime.org/XMLConfig_2008_09.xsd" key="viewRepresentation">
<entry key="jsCode" type="xstring" value="var body = document.getElementsByTagName(&quot;body&quot;)[0];%%00010var html = '&lt;script src=&quot;https://code.highcharts.com/highcharts.js&quot;&gt;&lt;/script&gt;';%%00010html += '&lt;script src=&quot;https://code.highcharts.com/modules/exporting.js&quot;&gt;&lt;/script&gt;';%%00010html += '&lt;script src=&quot;https://code.highcharts.com/modules/export-data.js&quot;&gt;&lt;/script&gt;';%%00010html += '&lt;div id=&quot;container&quot;&gt;&lt;/div&gt;';%%00010body.innerHTML = html;%%00010%%00010require.config({%%00010    packages: [{%%00010        name: 'highcharts',%%00010        main: 'highcharts'%%00010    }],%%00010    paths: {%%00010        // Change this to your server if you do not wish to use our CDN.%%00010        'highcharts': 'https://code.highcharts.com'%%00010    }%%00010});%%00010%%00010%%00010var data = knimeDataTable.getRows();%%00010// Extract Years column and x values%%00010var x_column_name = &quot;Years&quot;;%%00010var x_column = knimeDataTable.getColumnNames().indexOf(x_column_name);%%00010var x_values = knimeDataTable.getColumn(x_column);%%00010// Create dataset for values%%00010var dataset = [];%%00010%%00010for (var colID = 0; colID &lt; knimeDataTable.getNumColumns(); colID++) {%%00010  var colType = knimeDataTable.getColumnTypes()[colID];%%00010  var colName = knimeDataTable.getColumnNames()[colID];%%00010  //console.log('colomn name',colName)%%00010  if (colType === &quot;number&quot;) {%%00010    dataset.push({%%00010      name: colName,%%00010      //values: data.map(function(d) { // Data%%00010      //       return {x: d.data[x_column], y: d.data[colID]};%%00010      //       })%%00010      data: data.map(function(d) {%%00010        return [parseInt(d.data[x_column]),d.data[colID]];%%00010      })%%00010    });%%00010    console.log(dataset)%%00010  }%%00010}%%00010%%00010var chartData = {%%00010  series: dataset,%%00010  title: &quot;Calibrated livestock emission&quot;,%%00010  timeAxis: x_values,%%00010  unit: &quot;t&quot;%%00010};%%00010%%00010//console.log('chartData', chartData)%%00010%%00010require(['highcharts/modules/exporting', 'highcharts/modules/export-data'], function({Highcharts}) {%%00010    %%00010    Highcharts.chart('container', {%%00010    chart: {%%00010      renderTo: ServiceWorkerContainer,%%00010      type: &quot;area&quot;,%%00010      spacingBottom: 30%%00010    },%%00010    title: {%%00010      text: chartData.title%%00010    },%%00010    //subtitle: {%%00010    //    text: 'Source: Wikipedia.org'%%00010    //},%%00010    xAxis: {%%00010        allowDecimals: false,%%00010        labels: {%%00010            formatter: function () {%%00010                return this.value; // clean, unformatted number for year%%00010            }%%00010        }%%00010    },%%00010    yAxis: {%%00010      title: {%%00010        text: chartData.unit%%00010      },%%00010      //labels: {%%00010       // formatter: function() {%%00010       //   return this.value / 1000 + 'k';%%00010       // }%%00010      //}%%00010    },%%00010    tooltip: {%%00010      split: true,%%00010      //pointFormat: '&lt;b&gt;{point.y:,.0f}&lt;/b&gt;&lt;br/&gt; in {point.x}',%%00010      pointFormat: '&lt;span style=&quot;color:{series.color}&quot;&gt;{series.name}&lt;/span&gt;: &lt;b&gt;{point.y:,.0f}&lt;/b&gt; ({point.percentage:.1f}%)&lt;br/&gt;',%%00010      valueDecimals: 2%%00010      //valueSuffix: &quot; millions&quot;%%00010    },%%00010    plotOptions: {%%00010      area: {%%00010        stacking: &quot;normal&quot;,%%00010        lineColor: &quot;#666666&quot;,%%00010        lineWidth: 1,%%00010        marker: {%%00010          lineWidth: 1,%%00010          lineColor: &quot;#666666&quot;,%%00010          enabled:false,%%00010          symbol:'circle',%%00010          radius:2%%00010        }%%00010      }%%00010    },%%00010    responsive: {%%00010      rules: [%%00010        {%%00010          condition: {%%00010            maxWidth: 500%%00010          }%%00010        }%%00010      ]%%00010    },%%00010    series: chartData.series%%00010  });%%00010});%%00010"/>
<entry key="jsSVGCode" type="xstring" value=""/>
<entry key="cssCode" type="xstring" value="body {%%00010    font-family: sans-serif;%%00010}%%00010h1 {%%00010    font-size: 1.5em;%%00010    font-weight: bold;%%00010}%%00010.success {%%00010    color: #006633;%%00010    font-weight: bold;%%00010}%%00010%%00010.failure {%%00010    color: #990000;%%00010    font-weight: bold;%%00010}%%00010%%00010#container {%%00010    min-width: 300px;%%00010    max-width: 1600px;%%00010    height: 500px;%%00010    margin: 1em auto;%%00010}%%00010"/>
<config key="jsDependencies">
<entry key="array-size" type="xint" value="0"/>
</config>
<config key="jsExports">
<entry key="array-size" type="xint" value="0"/>
</config>
<config key="cssDependencies">
<entry key="array-size" type="xint" value="0"/>
</config>
<entry key="knimeDataTableJSON" type="xstring" value="{&quot;@class&quot;:&quot;org.knime.js.core.JSONDataTable&quot;,&quot;id&quot;:&quot;4b5d20c9-3227-4734-88ae-c9269d449bdc&quot;,&quot;spec&quot;:{&quot;@class&quot;:&quot;org.knime.js.core.JSONDataTableSpec&quot;,&quot;possibleValues&quot;:[[&quot;1990&quot;,&quot;1991&quot;,&quot;1992&quot;,&quot;1993&quot;,&quot;1994&quot;,&quot;1995&quot;,&quot;1996&quot;,&quot;1997&quot;,&quot;1998&quot;,&quot;1999&quot;,&quot;2000&quot;,&quot;2001&quot;,&quot;2002&quot;,&quot;2003&quot;,&quot;2004&quot;,&quot;2005&quot;,&quot;2006&quot;,&quot;2007&quot;,&quot;2008&quot;,&quot;2009&quot;,&quot;2010&quot;,&quot;2011&quot;,&quot;2012&quot;,&quot;2013&quot;,&quot;2014&quot;,&quot;2015&quot;,&quot;2016&quot;,&quot;2017&quot;,&quot;2018&quot;,&quot;2019&quot;,&quot;2020&quot;,&quot;2021&quot;,&quot;2022&quot;,&quot;2023&quot;,&quot;2024&quot;,&quot;2025&quot;,&quot;2026&quot;,&quot;2027&quot;,&quot;2028&quot;,&quot;2029&quot;,&quot;2030&quot;,&quot;2031&quot;,&quot;2032&quot;,&quot;2033&quot;,&quot;2034&quot;,&quot;2035&quot;,&quot;2036&quot;,&quot;2037&quot;,&quot;2038&quot;,&quot;2039&quot;,&quot;2040&quot;,&quot;2041&quot;,&quot;2042&quot;,&quot;2043&quot;,&quot;2044&quot;,&quot;2045&quot;,&quot;2046&quot;,&quot;2047&quot;,&quot;2048&quot;,&quot;2049&quot;,&quot;2050&quot;],null,null,null,null,null,null,null,null,null,null,null,null,null,null,null,null,null,null,null,null,null,null,null,null,null,null,null,null,null,null,null,null,null,null,null,null,null,null],&quot;numRows&quot;:61,&quot;numColumns&quot;:39,&quot;colNames&quot;:[&quot;Years&quot;,&quot;dat_livestock-enteric-fermentation-ch4-emissions_dairy-mutton-&amp;-goats&quot;,&quot;dat_livestock-enteric-fermentation-ch4-emissions_other-animals&quot;,&quot;dat_livestock-enteric-fermentation-ch4-emissions_pigs&quot;,&quot;dat_livestock-enteric-fermentation-ch4-emissions_dairy-cattle&quot;,&quot;dat_livestock-enteric-fermentation-ch4-emissions_non-dairy-cattle&quot;,&quot;dat_livestock-enteric-fermentation-ch4-emissions_mutton-&amp;-goats&quot;,&quot;dat_livestock-manure-left-on-pasture-n2o-emissions_dairy-mutton-&amp;-goats&quot;,&quot;dat_livestock-manure-left-on-pasture-n2o-emissions_other-animals&quot;,&quot;dat_livestock-manure-left-on-pasture-n2o-emissions_broilers-poultry&quot;,&quot;dat_livestock-manure-left-on-pasture-n2o-emissions_dairy-cattle&quot;,&quot;dat_livestock-manure-left-on-pasture-n2o-emissions_non-dairy-cattle&quot;,&quot;dat_livestock-manure-left-on-pasture-n2o-emissions_laying-poultry&quot;,&quot;dat_livestock-manure-left-on-pasture-n2o-emissions_mutton-&amp;-goats&quot;,&quot;dat_livestock-manure-left-on-pasture-n2o-emissions_pigs&quot;,&quot;dat_livestock-manure-applied-to-soils-n2o-emissions_dairy-mutton-&amp;-goats&quot;,&quot;dat_livestock-manure-applied-to-soils-n2o-emissions_other-animals&quot;,&quot;dat_livestock-manure-applied-to-soils-n2o-emissions_broilers-poultry&quot;,&quot;dat_livestock-manure-applied-to-soils-n2o-emissions_dairy-cattle&quot;,&quot;dat_livestock-manure-applied-to-soils-n2o-emissions_non-dairy-cattle&quot;,&quot;dat_livestock-manure-applied-to-soils-n2o-emissions_laying-poultry&quot;,&quot;dat_livestock-manure-applied-to-soils-n2o-emissions_mutton-&amp;-goats&quot;,&quot;dat_livestock-manure-applied-to-soils-n2o-emissions_pigs&quot;,&quot;dat_livestock-manure-treated-n2o-emissions_dairy-mutton-&amp;-goats&quot;,&quot;dat_livestock-manure-treated-n2o-emissions_other-animals&quot;,&quot;dat_livestock-manure-treated-n2o-emissions_broilers-poultry&quot;,&quot;dat_livestock-manure-treated-n2o-emissions_dairy-cattle&quot;,&quot;dat_livestock-manure-treated-n2o-emissions_non-dairy-cattle&quot;,&quot;dat_livestock-manure-treated-n2o-emissions_laying-poultry&quot;,&quot;dat_livestock-manure-treated-n2o-emissions_mutton-&amp;-goats&quot;,&quot;dat_livestock-manure-treated-n2o-emissions_pigs&quot;,&quot;dat_livestock-manure-treated-ch4-emissions_dairy-mutton-&amp;-goats&quot;,&quot;dat_livestock-manure-treated-ch4-emissions_laying-poultry&quot;,&quot;dat_livestock-manure-treated-ch4-emissions_dairy-cattle&quot;,&quot;dat_livestock-manure-treated-ch4-emissions_other-animals&quot;,&quot;dat_livestock-manure-treated-ch4-emissions_broilers-poultry&quot;,&quot;dat_livestock-manure-treated-ch4-emissions_non-dairy-cattle&quot;,&quot;dat_livestock-manure-treated-ch4-emissions_pigs&quot;,&quot;dat_livestock-manure-treated-ch4-emissions_mutton-&amp;-goats&quot;],&quot;minValues&quot;:[&quot;1990&quot;,0.0,0.0,3057.1045489535154,74755.97597006321,65141.66978424665,56553.10981315832,0.0,130.0,22.9144738743075,511.88354355671976,705.0175485539601,20.5,2076.5548260722617,0.0,0.0,5.4,657.8797527663395,780.7470876923572,667.8244697321766,589.0,305.90868314864264,181.59843802255364,0.0,1.8999999999999997,235.91492420593858,657.6676419465191,460.1631129772179,211.2,135.6230263356934,92.59309285344769,0.0,7768.9,13417.739276678018,263.6,1606.1697838748091,6857.017872025964,6419.877219289559,1343.3786378274137],&quot;hiddenColumns&quot;:[],&quot;maxValues&quot;:[&quot;2050&quot;,0.0,0.0,24438.0,335809.5,538821.0,357649.6,0.0,584.9166202767813,50.79999999999999,2299.5,5831.5,45.77952290219275,13121.7,0.0,0.0,24.371525844865886,1459.2,3507.1999999999994,5523.900000000001,1316.4027366179055,1934.8,1451.8000000000002,0.0,8.589964027288794,523.3,2954.2,3806.2999999999997,472.08925726986956,857.9,740.1,0.0,17363.864686523073,60273.5,1186.2407884193692,3463.6999999999994,56717.99999999999,51319.799999999996,8495.1],&quot;rowSizeValues&quot;:null,&quot;knimeTypes&quot;:[&quot;String&quot;,&quot;Number (double)&quot;,&quot;Number (double)&quot;,&quot;Number (double)&quot;,&quot;Number (double)&quot;,&quot;Number (double)&quot;,&quot;Number (double)&quot;,&quot;Number (double)&quot;,&quot;Number (double)&quot;,&quot;Number (double)&quot;,&quot;Number (double)&quot;,&quot;Number (double)&quot;,&quot;Number (double)&quot;,&quot;Number (double)&quot;,&quot;Number (double)&quot;,&quot;Number (double)&quot;,&quot;Number (double)&quot;,&quot;Number (double)&quot;,&quot;Number (double)&quot;,&quot;Number (double)&quot;,&quot;Number (double)&quot;,&quot;Number (double)&quot;,&quot;Number (double)&quot;,&quot;Number (double)&quot;,&quot;Number (double)&quot;,&quot;Number (double)&quot;,&quot;Number (double)&quot;,&quot;Number (double)&quot;,&quot;Number (double)&quot;,&quot;Number (double)&quot;,&quot;Number (double)&quot;,&quot;Number (double)&quot;,&quot;Number (double)&quot;,&quot;Number (double)&quot;,&quot;Number (double)&quot;,&quot;Number (double)&quot;,&quot;Number (double)&quot;,&quot;Number (double)&quot;,&quot;Number (double)&quot;],&quot;numExtensions&quot;:0,&quot;colTypes&quot;:[&quot;string&quot;,&quot;number&quot;,&quot;number&quot;,&quot;number&quot;,&quot;number&quot;,&quot;number&quot;,&quot;number&quot;,&quot;number&quot;,&quot;number&quot;,&quot;number&quot;,&quot;number&quot;,&quot;number&quot;,&quot;number&quot;,&quot;number&quot;,&quot;number&quot;,&quot;number&quot;,&quot;number&quot;,&quot;number&quot;,&quot;number&quot;,&quot;number&quot;,&quot;number&quot;,&quot;number&quot;,&quot;number&quot;,&quot;number&quot;,&quot;number&quot;,&quot;number&quot;,&quot;number&quot;,&quot;number&quot;,&quot;number&quot;,&quot;number&quot;,&quot;number&quot;,&quot;number&quot;,&quot;number&quot;,&quot;number&quot;,&quot;number&quot;,&quot;number&quot;,&quot;number&quot;,&quot;number&quot;,&quot;number&quot;],&quot;extensionNames&quot;:[],&quot;extensionTypes&quot;:[],&quot;rowColorValues&quot;:[&quot;#404040&quot;,&quot;#404040&quot;,&quot;#404040&quot;,&quot;#404040&quot;,&quot;#404040&quot;,&quot;#404040&quot;,&quot;#404040&quot;,&quot;#404040&quot;,&quot;#404040&quot;,&quot;#404040&quot;,&quot;#404040&quot;,&quot;#404040&quot;,&quot;#404040&quot;,&quot;#404040&quot;,&quot;#404040&quot;,&quot;#404040&quot;,&quot;#404040&quot;,&quot;#404040&quot;,&quot;#404040&quot;,&quot;#404040&quot;,&quot;#404040&quot;,&quot;#404040&quot;,&quot;#404040&quot;,&quot;#404040&quot;,&quot;#404040&quot;,&quot;#404040&quot;,&quot;#404040&quot;,&quot;#404040&quot;,&quot;#404040&quot;,&quot;#404040&quot;,&quot;#404040&quot;,&quot;#404040&quot;,&quot;#404040&quot;,&quot;#404040&quot;,&quot;#404040&quot;,&quot;#404040&quot;,&quot;#404040&quot;,&quot;#404040&quot;,&quot;#404040&quot;,&quot;#404040&quot;,&quot;#404040&quot;,&quot;#404040&quot;,&quot;#404040&quot;,&quot;#404040&quot;,&quot;#404040&quot;,&quot;#404040&quot;,&quot;#404040&quot;,&quot;#404040&quot;,&quot;#404040&quot;,&quot;#404040&quot;,&quot;#404040&quot;,&quot;#404040&quot;,&quot;#404040&quot;,&quot;#404040&quot;,&quot;#404040&quot;,&quot;#404040&quot;,&quot;#404040&quot;,&quot;#404040&quot;,&quot;#404040&quot;,&quot;#404040&quot;,&quot;#404040&quot;],&quot;containsMissingValues&quot;:[false,false,false,false,false,false,false,false,false,false,false,false,false,false,false,false,false,false,false,false,false,false,false,false,false,false,false,false,false,false,false,false,false,false,false,false,false,false,false],&quot;colorModels&quot;:[],&quot;filterIds&quot;:[null,null,null,null,null,null,null,null,null,null,null,null,null,null,null,null,null,null,null,null,null,null,null,null,null,null,null,null,null,null,null,null,null,null,null,null,null,null,null]},&quot;rows&quot;:[{&quot;data&quot;:[&quot;1990&quot;,0.0,0.0,22350.0,335809.5,524903.5,351194.0,0.0,130.0,35.0,2299.5,5680.9,24.7,12892.0,0.0,0.0,5.4,1004.6999999999999,3507.1999999999994,5381.2,709.8,1899.5,1327.7,0.0,1.9,360.2,2954.2,3708.0,254.5,842.1000000000001,676.9,0.0,9362.3,60273.5,263.6,2372.4,55253.0,46935.0,8342.1],&quot;rowKey&quot;:&quot;Row0&quot;},{&quot;data&quot;:[&quot;1991&quot;,0.0,0.0,22791.1,326388.6,518435.19999999995,349677.0,0.0,130.7,35.8,2235.0,5610.9,25.0,12836.2,0.0,0.0,5.4,1027.3,3408.8000000000006,5314.9,716.7,1891.3,1353.9000000000003,0.0,1.9,368.5,2871.4,3662.2999999999997,257.0,838.4999999999999,690.3,0.0,9453.7,58582.6,265.2,2428.6,54572.09999999999,47861.100000000006,8306.1],&quot;rowKey&quot;:&quot;Row1&quot;},{&quot;data&quot;:[&quot;1992&quot;,0.0,0.0,23121.1,313911.0,526737.0,356845.0,0.0,132.3,33.7,2149.5,5700.700000000001,24.600000000000005,13097.299999999997,0.0,0.0,5.5,965.3999999999999,3278.5,5400.0,705.4,1930.2,1373.5,0.0,1.8999999999999997,346.1,2761.6,3720.9,253.00000000000003,855.8,700.3000000000001,0.0,9304.2,56343.0,268.3,2266.3,55446.0,48554.1,8476.3],&quot;rowKey&quot;:&quot;Row2&quot;},{&quot;data&quot;:[&quot;1993&quot;,0.0,0.0,23559.0,312156.0,523430.99999999994,356008.0,0.0,133.1,35.6,2137.5,5665.0,24.6,13066.4,0.0,0.0,5.5,1021.4000000000001,3260.1,5366.1,706.2,1925.6999999999998,1399.5,0.0,1.9000000000000001,366.20000000000005,2746.1,3697.6,253.2,853.8,713.5,0.0,9315.0,56028.0,269.9,2402.9,55098.0,49473.9,8456.4],&quot;rowKey&quot;:&quot;Row3&quot;},{&quot;data&quot;:[&quot;1994&quot;,0.0,0.0,23676.0,317772.0,526566.0,350988.9,0.0,133.8,37.1,2176.0,5698.900000000001,24.5,12881.099999999999,0.0,0.0,5.6,1065.4,3318.8,5398.3,703.5,1898.6,1406.5,0.0,2.0,382.00000000000006,2795.6,3719.7,252.3,841.7999999999998,717.1000000000001,0.0,9279.3,57036.0,271.4,2493.5,55428.0,49719.600000000006,8337.1],&quot;rowKey&quot;:&quot;Row4&quot;},{&quot;data&quot;:[&quot;1995&quot;,0.0,0.0,22881.1,304551.0,527478.0,346880.0,0.0,134.6,38.2,2085.4,5708.8,24.000000000000004,12729.0,0.0,0.0,5.6,1094.5,3180.6999999999994,5407.6,688.3,1876.4,1359.3,0.0,2.0,392.49999999999994,2679.2,3726.0999999999995,246.8,831.9,693.0,0.0,9079.1,54663.0,273.0,2559.6,55523.99999999999,48050.1,8239.4],&quot;rowKey&quot;:&quot;Row5&quot;},{&quot;data&quot;:[&quot;1996&quot;,0.0,0.0,22770.0,302679.0,538821.0,337136.0,0.0,135.4,39.8,2072.6,5831.5,23.9,12371.9,0.0,0.0,5.6000000000000005,1144.3,3161.2,5523.900000000001,686.7000000000002,1823.7,1352.7,0.0,2.0,410.29999999999995,2662.8,3806.2999999999997,246.3,808.6,689.6,0.0,9058.0,54327.0,274.6,2661.1999999999994,56717.99999999999,47817.0,8008.000000000001],&quot;rowKey&quot;:&quot;Row6&quot;},{&quot;data&quot;:[&quot;1997&quot;,0.0,0.0,24216.0,289926.0,521834.99999999994,342986.8,0.0,136.1,46.5,1985.3,5647.700000000001,26.399999999999995,12584.5,0.0,0.0,5.7,1337.0999999999997,3028.0,5349.8,758.7,1855.4000000000003,1438.6,0.0,2.0,479.49999999999994,2550.6,3686.3,272.1,822.7000000000002,733.4,0.0,10007.5,52038.0,276.1,3149.9,54929.99999999999,50853.600000000006,8146.799999999999],&quot;rowKey&quot;:&quot;Row7&quot;},{&quot;data&quot;:[&quot;1998&quot;,0.0,0.0,24438.0,285363.0,517560.0,356150.5,0.0,136.9,43.0,1954.0,5601.400000000001,23.700000000000003,13066.0,0.0,0.0,5.7,1237.5,2980.3000000000006,5305.999999999999,681.5,1926.6999999999998,1451.8000000000002,0.0,2.0,443.7,2510.4,3656.0999999999995,244.4,854.3,740.1,0.0,8989.5,51219.00000000001,277.7,2914.7,54480.0,51319.799999999996,8459.4],&quot;rowKey&quot;:&quot;Row8&quot;},{&quot;data&quot;:[&quot;1999&quot;,0.0,0.0,21852.0,285480.0,512031.0,357649.6,0.0,138.4,41.8,1954.8000000000002,5541.6,23.2,13121.7,0.0,0.0,5.8,1199.1,2981.5,5249.3,666.0,1934.8,1298.1,0.0,2.0,429.99999999999994,2511.5,3617.0,238.8,857.9,661.8,0.0,8784.9,51240.00000000001,280.8,2845.2,53898.0,45889.2,8495.1],&quot;rowKey&quot;:&quot;Row9&quot;},{&quot;data&quot;:[&quot;2000&quot;,0.0,0.0,19446.0,275418.0,500403.0,338497.80000000005,0.0,230.70000000000002,48.0,1885.9,5415.699999999999,23.5,12419.300000000001,0.0,0.0,9.6,1379.0000000000002,2876.4000000000005,5130.1,673.9,1831.2000000000003,1155.2,0.0,3.4,494.50000000000006,2422.9,3534.9,241.70000000000002,811.9000000000001,588.9,0.0,8889.2,49434.0,468.00000000000006,3271.2000000000003,52674.0,40836.6,8040.200000000001],&quot;rowKey&quot;:&quot;Row10&quot;},{&quot;data&quot;:[&quot;2001&quot;,0.0,0.0,17535.1,263367.0,475893.00000000006,294109.1,0.0,238.4,50.79999999999999,1803.4000000000003,5150.5,24.7,10792.600000000002,0.0,0.0,9.9,1459.2,2750.6,4878.8,708.9,1591.0000000000002,1041.7,0.0,3.5000000000000004,523.3,2316.9,3361.7,254.19999999999996,705.4000000000001,531.1,0.0,9349.9,47271.0,483.6000000000001,3463.6999999999994,50093.99999999999,36823.5,6985.9],&quot;rowKey&quot;:&quot;Row11&quot;},{&quot;data&quot;:[&quot;2002&quot;,0.0,0.0,16764.0,260582.4,462600.6,287048.2,0.0,246.10000000000002,46.4,1784.4,5006.6,24.0,10533.6,0.0,0.0,10.3,1329.2,2721.5,4742.5,688.5,1552.8,995.8999999999999,0.0,3.6000000000000005,476.69999999999993,2292.4,3267.8000000000006,246.9,688.4,507.69999999999993,0.0,9081.1,46771.2,499.20000000000005,3163.2999999999997,48694.8,35204.4,6818.2],&quot;rowKey&quot;:&quot;Row12&quot;},{&quot;data&quot;:[&quot;2003&quot;,0.0,0.0,15140.400000000001,256499.1,474507.9,287234.9,0.0,253.80000000000004,44.3,1756.4000000000003,5135.5,23.3,10544.199999999999,0.0,0.0,10.600000000000001,1272.1,2678.9,4864.6,670.2,1553.6,899.4000000000001,0.0,3.7,456.1000000000001,2256.5,3352.0,240.30000000000004,688.8,458.5,0.0,8840.4,46038.3,514.8,3063.9000000000005,49948.200000000004,31794.8,6822.899999999999],&quot;rowKey&quot;:&quot;Row13&quot;},{&quot;data&quot;:[&quot;2004&quot;,0.0,0.0,15481.8,249525.89999999997,479843.1,287229.0,0.0,269.2,44.4,1708.6,5193.2,23.0,10543.1,0.0,0.0,11.2,1274.1,2606.0,4919.3,661.8,1553.6,919.7,0.0,3.9,456.90000000000003,2195.2,3389.6,237.3,688.8,468.9,0.0,8729.1,44786.7,546.0,3069.6,50509.799999999996,32511.8,6822.699999999999],&quot;rowKey&quot;:&quot;Row14&quot;},{&quot;data&quot;:[&quot;2005&quot;,0.0,0.0,14590.800000000001,233730.9,500032.49999999994,282484.4,0.0,284.6,42.0,1600.5,5411.7,23.6,10369.800000000001,0.0,0.0,11.9,1207.7,2441.1,5126.299999999999,677.0,1527.9000000000003,866.8000000000001,0.0,4.2,433.1000000000001,2056.2,3532.3000000000006,242.8,677.4,441.9,0.0,8929.1,41951.69999999999,577.2,2906.6,52635.0,30640.7,6710.000000000001],&quot;rowKey&quot;:&quot;Row15&quot;},{&quot;data&quot;:[&quot;2006&quot;,0.0,0.0,14799.100000000002,231519.6,490211.4,278266.0,0.0,298.4,41.1,1585.3000000000002,5305.4,22.8,10216.5,0.0,0.0,12.400000000000002,1180.2,2418.0,5025.6,656.2,1505.0,879.1000000000001,0.0,4.4,423.19999999999993,2036.8,3462.9,235.3,667.2,448.20000000000005,0.0,8655.2,41554.8,605.3,2829.9,51601.2,31077.9,6609.9],&quot;rowKey&quot;:&quot;Row16&quot;},{&quot;data&quot;:[&quot;2007&quot;,0.0,0.0,14502.0,228618.0,475950.0,272043.0,0.0,295.3,37.1,1565.4999999999998,5151.1,22.9,9987.8,0.0,0.0,12.3,1065.6,2387.7,4879.4,658.8,1471.3,861.5,0.0,4.3,382.0,2011.1999999999998,3362.1,236.20000000000002,652.3,439.2,0.0,8689.6,41034.0,599.0,2588.9,50100.0,30454.2,6462.1],&quot;rowKey&quot;:&quot;Row17&quot;},{&quot;data&quot;:[&quot;2008&quot;,0.0,0.0,14142.0,223353.0,467286.0,265508.0,0.0,296.1,39.4,1529.4,5057.3,21.3,9747.8,0.0,0.0,12.3,1130.5,2332.7,4790.6,611.9,1436.0,840.1000000000001,0.0,4.3,405.40000000000003,1964.9000000000003,3300.8999999999996,219.4,636.6,428.3,0.0,8070.9,40089.0,600.6,2738.0,49187.99999999999,29698.2,6306.9],&quot;rowKey&quot;:&quot;Row18&quot;},{&quot;data&quot;:[&quot;2009&quot;,0.0,0.0,13620.0,218088.00000000003,465177.00000000006,252000.00000000003,0.0,297.6,39.6,1493.4000000000003,5034.5,20.5,9252.0,0.0,0.0,12.4,1136.6,2277.7,4768.9,589.0,1362.9,809.1,0.0,4.4,407.6,1918.6000000000001,3286.0000000000005,211.2,604.2,412.49999999999994,0.0,7768.9,39144.0,603.7,2770.1,48966.0,28601.999999999996,5986.0],&quot;rowKey&quot;:&quot;Row19&quot;},{&quot;data&quot;:[&quot;2010&quot;,0.0,0.0,13380.0,216450.0,470934.00000000006,249137.00000000003,0.0,300.0,35.8,1482.2,5096.8,22.6,9148.1,0.0,0.0,12.500000000000002,1025.9,2260.6,4828.0,650.4,1347.4000000000003,794.8,0.0,4.4,367.8,1904.1999999999998,3326.7000000000003,233.2,597.3,405.19999999999993,0.0,8578.2,38850.0,608.4,2492.9,49572.00000000001,28098.0,5918.1],&quot;rowKey&quot;:&quot;Row20&quot;},{&quot;data&quot;:[&quot;2011&quot;,0.0,0.0,13323.1,212355.00000000003,462725.99999999994,253541.99999999997,0.0,296.1,35.2,1454.1,5008.0,23.400000000000002,9309.7,0.0,0.0,12.3,1010.3,2217.8,4743.8,671.0999999999999,1371.2000000000003,791.5,0.0,4.3,362.3,1868.2,3268.7,240.7,607.9,403.50000000000006,0.0,8851.9,38115.0,600.6,2448.8,48708.0,27978.3,6022.700000000001],&quot;rowKey&quot;:&quot;Row21&quot;},{&quot;data&quot;:[&quot;2012&quot;,0.0,0.0,13443.099999999999,210366.0,461814.00000000006,258210.00000000003,0.0,300.0,34.8,1440.5000000000002,4998.1,22.4,9481.6,0.0,0.0,12.500000000000002,1001.4,2197.1,4734.5,643.8,1396.4,798.6,0.0,4.4,359.0,1850.7,3262.3,230.89999999999998,619.1,407.1,0.0,8491.9,37758.0,608.4,2430.4,48612.0,28230.299999999996,6133.6],&quot;rowKey&quot;:&quot;Row22&quot;},{&quot;data&quot;:[&quot;2013&quot;,0.0,0.0,14655.100000000002,209898.0,458850.00000000006,263338.0,0.0,303.8,36.1,1437.3,4966.0,22.6,9669.5,0.0,0.0,12.700000000000001,1037.2,2192.2,4704.1,649.2,1424.2,870.6000000000001,0.0,4.4,371.90000000000003,1846.5,3241.4,232.79999999999998,631.4,443.8,0.0,8563.1,37674.0,616.2,2515.6,48300.0,30775.5,6255.4],&quot;rowKey&quot;:&quot;Row23&quot;},{&quot;data&quot;:[&quot;2014&quot;,0.0,0.0,14445.1,216566.99999999997,455202.0,270444.0,0.0,307.6,37.3,1483.0,4926.5,22.6,9930.3,0.0,0.0,12.8,1074.5,2261.8,4666.7,648.9,1462.6,858.1,0.0,4.5,385.3,1905.2,3215.6000000000004,232.7,648.4,437.5,0.0,8558.7,38871.0,624.0,2622.0,47916.0,30334.499999999996,6424.2],&quot;rowKey&quot;:&quot;Row24&quot;},{&quot;data&quot;:[&quot;2015&quot;,0.0,0.0,14217.1,222417.0,457026.0,267201.0,0.0,310.5,36.2,1523.0000000000002,4946.3,25.300000000000004,9811.6,0.0,0.0,12.9,1039.6,2322.9,4685.4,725.2,1445.0,844.6,0.0,4.5,372.8,1956.7,3228.5000000000005,260.1,640.6,430.6,0.0,9565.6,39921.0,629.8,2521.5,48108.0,29855.7,6347.2],&quot;rowKey&quot;:&quot;Row25&quot;},{&quot;data&quot;:[&quot;2016&quot;,0.0,0.0,14598.000000000002,221948.99999999997,463752.0,272064.0,0.0,322.4,36.8,1519.8,5019.1,25.7,9990.4,0.0,0.0,13.399999999999999,1055.3,2318.0,4754.3,738.5,1471.3,867.2000000000002,0.0,4.7,378.30000000000007,1952.6,3276.0,264.8,652.3,442.1000000000001,0.0,9740.3,39837.0,653.8,2568.4000000000005,48816.0,30655.8,6462.7],&quot;rowKey&quot;:&quot;Row26&quot;},{&quot;data&quot;:[&quot;2017&quot;,0.0,0.0,14907.0,221949.0,462099.00000000006,279176.0,0.0,320.50000000000006,39.3,1519.8,5001.2,26.0,10251.0,0.0,0.0,13.400000000000002,1131.6,2318.0,4737.4,745.5,1509.8,885.6,0.0,4.7,405.9,1952.6,3264.2999999999997,267.3,669.4,451.5,0.0,9833.4,39837.0,650.1000000000001,2755.3,48642.0,31304.7,6631.600000000001],&quot;rowKey&quot;:&quot;Row27&quot;},{&quot;data&quot;:[&quot;2018&quot;,0.0,0.0,15106.415625139958,222629.4720891019,469688.0062734955,276911.5385025156,0.0,398.6247580486813,43.363761318581965,1524.478316399609,5083.357153658488,27.882697190115923,10168.497518822986,0.0,0.0,16.665946836968708,1247.4921460627477,2325.1582018875256,4815.200292072335,801.9546877749225,1497.5239534554805,897.4137880191088,0.0,5.802218528426143,447.3712732542984,1958.555055329318,3317.8625728127913,287.5843533291018,663.9298986432411,457.5226471719133,0.0,10578.111488501452,39959.136015992655,808.6070502381116,3045.7365025881836,49440.84276563111,31723.263625430733,6577.83535903183],&quot;rowKey&quot;:&quot;Row28&quot;},{&quot;data&quot;:[&quot;2019&quot;,0.0,0.0,15153.645023700114,222320.5676553924,465680.6345355329,277749.20336990297,0.0,383.93409390247473,43.16543231629034,1522.3615997555667,5039.985977887342,27.97875728967752,10199.236345009727,0.0,0.0,16.050047216841964,1241.7084090822984,2321.9310806459935,4774.116571702856,804.711894479668,1502.0650930141985,900.217593867395,0.0,5.589949734085873,445.2964447146669,1955.8385528663155,3289.555559139561,288.57351295217416,665.9428940201287,458.9536330049521,0.0,10614.479647118285,39903.691630455054,778.8018699207456,3031.6134917179706,49019.014161635045,31822.444708393985,6597.7334882810355],&quot;rowKey&quot;:&quot;Row29&quot;},{&quot;data&quot;:[&quot;2020&quot;,0.0,0.0,15200.439160536449,221951.2628701577,461691.2590699989,278586.7092287164,0.0,366.36113276224086,42.96429120029311,1519.831290318628,4996.809573558956,28.07413027595299,10229.969204651186,0.0,0.0,15.313798719407615,1235.8445116161106,2318.0731367873523,4733.217356046585,807.4493001888851,1506.6054395320953,902.9955307007128,0.0,5.33558435359785,443.1928757724868,1952.590682358276,3261.37565442496,289.55557466811587,667.9555358240636,460.3714397150734,0.0,10650.586618874579,39837.40615618216,743.1504580064365,3017.2947897578374,48599.07990210515,31920.711747764533,6617.627840395399],&quot;rowKey&quot;:&quot;Row30&quot;},{&quot;data&quot;:[&quot;2021&quot;,0.0,0.0,14793.068223399434,217012.37043157016,444098.8115086305,271106.9816679569,0.0,379.27953194655294,42.22574271363492,1486.0103521915378,4806.409329349771,28.714171004984355,9955.285840157838,0.0,0.0,15.852101714470333,1214.524094612754,2266.490149723453,4552.860689001551,825.8519257223753,1466.1656682716773,878.7934351317336,0.0,5.525267926745351,435.54637586745065,1909.142365585653,3137.1039405005545,296.1552776411756,650.0261900884159,448.0340626827012,0.0,10893.324235268901,38950.93828258952,769.3497444316174,2965.239286040297,46747.243316697946,31065.238420880178,6439.952266848863],&quot;rowKey&quot;:&quot;Row31&quot;},{&quot;data&quot;:[&quot;2022&quot;,0.0,0.0,14426.371691596563,211028.95947969545,429687.5779750507,265380.5829298266,0.0,391.8550305656026,41.638451798177606,1445.037058013475,4650.438850856693,29.350998180826583,9744.98725158815,0.0,0.0,16.375959996902765,1197.5566562930003,2203.998193233893,4405.117573411929,844.1618681668341,1435.207495618865,857.0077310321756,0.0,5.710059920991398,429.46093988223737,1856.5049611520385,3035.304185427373,302.72176279166285,636.3005372458282,436.92855257905507,0.0,11134.839299704154,37876.99272712483,794.8531229508513,2923.811567893399,45230.27136579482,30295.18078195527,6303.925764293979],&quot;rowKey&quot;:&quot;Row32&quot;},{&quot;data&quot;:[&quot;2023&quot;,0.0,0.0,14059.460210605846,205103.1223750107,415454.6653867897,259601.55578064115,0.0,404.09536500492345,41.05450009604686,1404.458083485138,4496.398313511099,29.98461594391272,9532.756981898285,0.0,0.0,16.88570140868563,1180.687386847995,2142.1075894797436,4259.202618304098,862.3792485556895,1403.9642433449358,835.2093502178229,0.0,5.8900689130085935,423.41072732626975,1804.3740005298566,2934.764027701129,309.2550733800766,622.448507632519,425.8165049621655,0.0,11375.133408843489,36813.38093910449,819.6763004026377,2882.6235841023467,43732.07004071471,29524.67175271241,6166.649111510616],&quot;rowKey&quot;:&quot;Row33&quot;},{&quot;data&quot;:[&quot;2024&quot;,0.0,0.0,13692.281628680663,199237.71890513983,401394.9665012792,253767.08894550372,0.0,416.00805859038076,40.47365565756297,1364.2930100494707,4344.2324424101125,30.615028433629494,9318.491811278653,0.0,0.0,17.381644752333457,1163.909597508194,2080.8482055187683,4115.063464137106,880.5041878888784,1372.4207012370898,813.395194675633,0.0,6.065400499101735,417.393339356027,1752.7746432378033,2835.4473909306407,315.7552526551542,608.4633579797184,414.69634029483643,0.0,11614.208158907973,35760.61621374306,843.8345510266669,2841.659003691682,42252.101736976765,28753.601815205875,6028.055528676157],&quot;rowKey&quot;:&quot;Row34&quot;},{&quot;data&quot;:[&quot;2025&quot;,0.0,0.0,13324.79093053955,193435.40924338248,387504.01628390857,247874.6421774427,0.0,427.60042887314137,39.89570068294501,1324.5600522036837,4193.892913164878,31.24223978831727,9102.09847307635,0.0,0.0,17.86410009997347,1147.2170080742233,2020.2478235816818,3972.654335246709,898.5368071328465,1340.5631244149822,791.5625903623859,0.0,6.2361573971130175,411.4065236611766,1701.730292759652,2737.322735230939,322.222343853872,594.3389946874065,403.5666951735342,0.0,11852.065145676608,34719.176018043014,867.3427312553082,2800.9024932451193,40789.89645093775,27981.876437967945,5888.084674042332],&quot;rowKey&quot;:&quot;Row35&quot;},{&quot;data&quot;:[&quot;2026&quot;,0.0,0.0,12940.782910678448,187497.43321864403,373309.07051027234,241618.42131154292,0.0,438.4179540538395,39.28942701080547,1283.898188345908,4040.2632919571574,31.86623907849471,8872.34806738992,0.0,0.0,18.314084924082483,1129.7122556342504,1958.2305838390612,3827.128702752,916.4767938983138,1306.7376884893213,768.7488650890564,0.0,6.395705064289893,405.12847490993295,1649.4923746534544,2637.0506023443336,328.65623480847097,579.3421948661877,391.9367634165906,0.0,12088.70024879045,33653.38544950022,889.2789106770892,2758.1631640634923,39295.69163266025,27175.464913843043,5739.472626136447],&quot;rowKey&quot;:&quot;Row36&quot;},{&quot;data&quot;:[&quot;2027&quot;,0.0,0.0,12556.160608756398,181639.3604897956,359267.148808791,235287.1487380593,0.0,448.90379456470407,38.68517032633944,1243.7835439126652,3888.2898278584303,32.48704557755672,8639.84268447511,0.0,0.0,18.750119765868227,1112.267698622592,1897.047905082017,3683.1718884328716,934.3247044369563,1272.5058500927832,745.8987452037436,0.0,6.55050073197479,398.87203224787754,1597.9573433589726,2537.8593722833293,335.0571248529005,564.1652313077949,380.28819823439636,0.0,12324.120805616985,32601.936498168445,910.5420136776262,2715.5708592642063,37817.59461145169,26367.76340589647,5589.077778645646],&quot;rowKey&quot;:&quot;Row37&quot;},{&quot;data&quot;:[&quot;2028&quot;,0.0,0.0,12170.518087896555,175873.5735000831,345349.7258311471,228861.68680912026,0.0,459.065453761525,38.08117634538318,1204.3009065736694,3737.6637956326017,33.10466342061817,8403.87960048917,0.0,0.0,19.172522413443655,1094.832890043306,1836.82910896393,3540.491452732132,952.0806596122251,1237.764097139092,722.9881163089739,0.0,6.700649870431517,392.6191047282779,1547.2341335887133,2439.5475431602686,341.425057187951,548.7622122359971,368.6087049404961,0.0,12558.328410575703,31567.051653861072,931.1472734302242,2673.0024136812076,36352.60271906812,25557.919452308102,5436.445530445182],&quot;rowKey&quot;:&quot;Row38&quot;},{&quot;data&quot;:[&quot;2029&quot;,0.0,0.0,11783.059489797482,170222.90284410276,331502.7901161006,222304.95398657912,0.0,468.9102352427519,37.47398083827825,1165.6066077134917,3587.80063800959,33.719096741749034,8163.097192983306,0.0,0.0,19.581602179832398,1077.3082378007678,1777.8126377149458,3398.533675116138,969.7447802541282,1202.3118669308312,699.9697010272849,0.0,6.8462551556346245,386.3339775700618,1497.5235971391544,2341.7335791180217,347.76007500266826,533.0442186365696,356.8741792158973,0.0,12791.324657644649,30552.828715608193,951.1095175185801,2630.2146762501125,34895.03053853691,24744.26176166563,5280.695036142672],&quot;rowKey&quot;:&quot;Row39&quot;},{&quot;data&quot;:[&quot;2030&quot;,0.0,0.0,11392.240805628555,164730.4358464487,317624.0935783647,215545.48054683648,0.0,478.4452494538065,36.856769318895985,1127.995686570188,3437.593740626689,34.33034967397535,7914.87111008379,0.0,0.0,19.97766018316941,1059.4978671957329,1720.4484949532527,3256.25031825472,987.3171871592581,1165.7626047609622,676.7517787818164,0.0,6.98741656165326,379.94640831850467,1449.2047934393097,2243.6952005608205,354.0622214743636,516.8398722685447,345.03785731805266,0.0,13023.111140360787,29567.00130577285,970.4431813462543,2586.729425745906,33434.115113512074,23923.547936805535,5120.128583618442],&quot;rowKey&quot;:&quot;Row40&quot;},{&quot;data&quot;:[&quot;2031&quot;,0.0,0.0,10983.494184457533,159332.91450530637,303200.93459860765,208226.66958739102,0.0,487.46003419954667,36.19347663983384,1091.0349797255071,3281.4942175648853,34.9371857058695,7646.107119073963,0.0,0.0,20.35191355353272,1040.3651557653207,1664.0760109724881,3108.385217269246,1004.7623212921173,1126.1876427878426,652.4689549761298,0.0,7.121055770319662,373.08465495605947,1401.7212164602854,2141.8106842699976,360.3187446030368,499.29410099932386,332.65852046994274,0.0,13253.218820936161,28598.215424029357,988.7213945673589,2540.0157854812574,31915.88785248502,23065.18569249967,4946.275468737594],&quot;rowKey&quot;:&quot;Row41&quot;},{&quot;data&quot;:[&quot;2032&quot;,0.0,0.0,10562.798513154336,154340.05420852502,288203.7774849966,200311.08424943246,0.0,496.16916688545234,35.48131877356522,1056.8452649242915,3119.1824089998086,35.54085544964548,7355.4306648640795,0.0,0.0,20.71332707171254,1019.8303325099997,1611.9298568057445,2954.635577016459,1022.1161515726117,1083.3844364041465,627.4764084077367,0.0,7.250301954984298,365.72011309012987,1357.7975704930332,2035.871386813557,366.5425430585362,480.3171089109775,319.91725021282963,0.0,13482.122144107416,27702.06101178655,1006.3794058104517,2489.879004110049,30337.239735262803,22181.73060838171,4758.246405719749],&quot;rowKey&quot;:&quot;Row42&quot;},{&quot;data&quot;:[&quot;2033&quot;,0.0,0.0,10119.528726561357,150067.7772437364,271985.5996573023,191325.96600845922,0.0,504.57950261433325,34.670468960331306,1027.5898135422551,2943.6556954381044,36.14136302773553,7025.4822087305265,0.0,0.0,21.062190952929143,996.461594530199,1567.3095233944805,2788.368190868811,1039.3787984789515,1034.795976204731,601.1429696155649,0.0,7.375251581640713,357.3393287374765,1320.213170522081,1921.3067360955042,372.7336599050021,458.77525180740236,306.49224168102046,0.0,13709.822699210643,26935.242069388594,1023.4311318126831,2432.823395938486,28630.063121821295,21250.87019475217,4544.811354258292],&quot;rowKey&quot;:&quot;Row43&quot;},{&quot;data&quot;:[&quot;2034&quot;,0.0,0.0,9634.079984855272,147162.239831118,253426.5089772053,180440.1019908267,0.0,512.6977198726034,33.66721145759152,1007.6931648891234,2742.7936677085277,36.73871256153104,6625.7399531749115,0.0,0.0,21.39878791911254,967.5661682841533,1536.9634620591737,2598.1020457397617,1056.5503824560315,975.9264448482529,572.3040388885577,0.0,7.4959986456984025,346.9766573197079,1294.652554227443,1790.2058024495088,378.892138194875,432.67532053525406,291.78971580994624,0.0,13936.32207514217,26413.735354303237,1039.8901307072365,2362.2746747720566,26676.474629179505,20231.434559461744,4286.225447596461],&quot;rowKey&quot;:&quot;Row44&quot;},{&quot;data&quot;:[&quot;2035&quot;,0.0,0.0,9071.686342956313,147033.3023975125,230769.64743672367,166323.99982230304,0.0,520.5303261826325,32.30302248635362,1006.8092994032927,2497.5821396368915,37.33290817138299,6107.385625466082,0.0,0.0,21.72339343871439,928.3021755544142,1535.6162426241835,2365.8260265674594,1073.6310239154443,899.5848830693192,538.8943962035678,0.0,7.612634751050259,332.8957759473827,1293.5189251704912,1630.1581165519915,385.01802096890026,398.82922387812806,274.7567019709721,0.0,14161.621860358733,26390.59273801507,1055.769613499927,2266.4116217702112,24291.5418354446,19050.415699267272,3950.9075461541665],&quot;rowKey&quot;:&quot;Row45&quot;},{&quot;data&quot;:[&quot;2036&quot;,0.0,0.0,8522.125082955292,146869.05952063587,209954.1991762781,153182.12850756588,0.0,527.4488139830025,30.989918368975385,1005.6836821195824,2272.2999300678257,37.920752056762154,5624.806945259029,0.0,0.0,22.009784473192624,890.5110714969687,1533.9002942242073,2152.4280279909444,1090.5287621060243,828.5114866950399,506.24718842042927,0.0,7.715962076224302,319.343125457697,1292.0746966706256,1483.1180964292914,391.07832972056013,367.31879028086695,258.1123045541732,0.0,14384.509056076502,26361.113247293626,1069.7948253846835,2174.1446955950514,22100.442018555597,17896.34466336098,3638.731801201816],&quot;rowKey&quot;:&quot;Row46&quot;},{&quot;data&quot;:[&quot;2037&quot;,0.0,0.0,8065.579327635766,143769.20537180008,194820.22761000547,143884.83643315692,0.0,534.0714157388862,30.08269987399415,984.4565321428475,2108.5074159229343,38.5054654365621,5283.401899348272,0.0,0.0,22.283768519221844,864.3873175544118,1501.5248381966155,1997.2759600523082,1107.336236362091,778.2312524167556,479.1255881722728,0.0,7.815015998732331,309.97449869245094,1264.804529669683,1376.2119989189591,397.1062859308088,345.0269869035499,244.285059654764,0.0,14606.20561234121,25804.729169297458,1083.2197218280687,2110.3632132740568,20507.392380000576,16937.60489924579,3417.8812838090994],&quot;rowKey&quot;:&quot;Row47&quot;},{&quot;data&quot;:[&quot;2038&quot;,0.0,0.0,7651.992927229517,139179.92765552836,182255.0977768713,136258.39208246957,0.0,540.4048465146948,29.367272523984795,953.0306369715585,1972.5170575753498,39.087052408543165,5003.351098311906,0.0,0.0,22.54562966699605,843.777372496945,1453.5938812917307,1868.459410010888,1124.0535664262238,736.9874720716657,454.5560440193594,0.0,7.9098911940917676,302.58318278673437,1224.4311750282623,1287.452168396744,403.10193240189164,326.7414939443545,231.75890747411006,0.0,14826.713108783228,24981.01265612048,1096.057934661523,2060.0435288854005,19184.747134407506,16069.079185565193,3236.7205579508523],&quot;rowKey&quot;:&quot;Row48&quot;},{&quot;data&quot;:[&quot;2039&quot;,0.0,0.0,7258.625251646707,133896.85237157356,170945.58759929976,129376.66616727624,0.0,546.4556537725936,28.745945654760266,916.8540473889058,1850.1160671099858,39.66551706943147,4750.647151292414,0.0,0.0,22.79564489586163,825.8735347485026,1398.4169490023444,1752.5153613570865,1140.680872007899,699.7711077436935,431.18766694093694,0.0,8.000679993329681,296.16231301592086,1177.9541109729976,1207.5620015343793,409.0653119244293,310.2415625592077,219.84509760293352,0.0,15046.033124595982,24032.76837438501,1108.3227554149557,2016.3307454519568,17994.27237887366,15243.012514033324,3073.2500853915685],&quot;rowKey&quot;:&quot;Row49&quot;},{&quot;data&quot;:[&quot;2040&quot;,0.0,0.0,6874.868170604853,128329.49691406424,160303.16806070317,122820.21332509532,0.0,552.2302225700358,28.172479090848466,878.7309305232286,1734.934891192659,40.24086351491919,4509.888093963514,0.0,0.0,23.034084294832756,809.3468930517384,1340.271042334039,1643.4102759586392,1157.218272783498,664.3135403614426,408.3902906750616,0.0,8.087472455688069,290.2353315192564,1128.9760483691969,1132.3841276470023,414.99646727741987,294.5214046949493,208.2223389162118,0.0,15264.167238536033,23033.4994461141,1120.0271458698744,1975.9803782583058,16874.017690600336,14437.127957953946,2917.506241822079],&quot;rowKey&quot;:&quot;Row50&quot;},{&quot;data&quot;:[&quot;2041&quot;,0.0,0.0,6491.05737387711,122606.3253012578,149948.62756698567,116309.90949651744,0.0,557.000761704325,27.6152103503809,839.5409431966954,1622.8693848047253,40.81305506006719,4270.824597205108,0.0,0.0,23.23059785725768,793.2876361350378,1280.4978402038762,1537.256516938454,1173.6647156937406,629.1050634138298,385.58982027532846,0.0,8.159603665218196,284.47597422287885,1078.6271433063619,1059.23979329717,420.8950206782609,278.91169570310524,196.59792465807027,0.0,15481.101560512672,22006.263515610382,1129.6950295066276,1936.7711626979815,15784.066059682704,13631.130599678032,2762.8586350331307],&quot;rowKey&quot;:&quot;Row51&quot;},{&quot;data&quot;:[&quot;2042&quot;,0.0,0.0,6109.485301277959,116906.59469200783,139864.4575921211,109836.29911900953,0.0,561.4854516619857,27.0728497273532,800.5115421179822,1513.7300559681032,41.382136772920106,4033.1094490577098,0.0,0.0,23.415148611504776,777.6586294569468,1220.9695017146605,1433.8745879489175,1190.0214986703559,594.0945381522055,362.92243381892985,0.0,8.227585042651691,278.8709237854453,1028.484406354547,988.0053196603241,426.76143744653456,263.38976323335544,185.04128718760177,0.0,15696.853210937177,20983.234944719363,1138.7830336376726,1898.6124343918443,14722.574483381168,12829.834531071238,2609.0826549058884],&quot;rowKey&quot;:&quot;Row52&quot;},{&quot;data&quot;:[&quot;2043&quot;,0.0,0.0,5729.030599864915,111279.83219448965,129990.57734119195,103355.36697253228,0.0,565.6908872929297,26.54010692160777,761.9818606758566,1406.8666600396514,41.94811274581976,3795.126437450868,0.0,0.0,23.588015351979017,762.3078392995375,1162.203286238775,1332.6485466805386,1206.2887412831847,559.0438928982841,340.32151874722047,0.0,8.291509761186138,273.365659791078,978.9835522353652,918.2562963263285,432.5957603237791,247.85005895134603,173.51846369036764,0.0,15911.423767159855,19973.303214395586,1147.304545402687,1861.1330091385535,13683.218667493891,12030.88492648238,2455.1327513983583],&quot;rowKey&quot;:&quot;Row53&quot;},{&quot;data&quot;:[&quot;2044&quot;,0.0,0.0,5349.16887190595,105750.7199242492,120298.50364770151,96846.20245454172,0.0,569.6235038339612,26.014401433700776,724.120906548999,1301.9709283352786,42.51098707007591,3556.107745044254,0.0,0.0,23.74947010119239,747.1610985163813,1104.456972075863,1233.2863863226619,1222.466563069034,523.840021561155,317.7559239131366,0.0,8.351468761284195,267.9335852802581,930.3417228350722,849.7915188033236,438.3980320399313,232.24243773748287,162.0135715345051,0.0,16124.814806094968,18980.89844794217,1155.2726278610533,1824.1518106159826,12663.000383968581,11233.180557935839,2300.51220811679],&quot;rowKey&quot;:&quot;Row54&quot;},{&quot;data&quot;:[&quot;2045&quot;,0.0,0.0,4969.660039607414,100331.96553202736,110774.62634692503,90298.90356520547,0.0,573.2895817096785,25.494478340750447,687.0156925073906,1198.8955602327394,43.070763835966154,3315.6897862804967,0.0,0.0,23.899778313451257,732.182328176821,1047.8632762651175,1135.6485764692036,1238.5550835316726,488.4293605584653,295.2113878153841,0.0,8.40755081783058,262.56176195263265,882.6707151205911,782.5148456401147,444.16829531332576,216.54315249744542,150.51933939350005,0.0,16337.027904220657,18008.301505748506,1162.700029739665,1787.5807531742462,11660.486983886845,10436.217265389443,2144.9858101439063],&quot;rowKey&quot;:&quot;Row55&quot;},{&quot;data&quot;:[&quot;2046&quot;,0.0,0.0,4586.735859916429,94961.48800684589,101331.4090950277,83641.98574278117,0.0,576.139372484016,24.968482913594357,650.2411216643641,1096.6931642443158,43.618601172856856,3071.2477302539382,0.0,0.0,24.016027598692013,717.0310590575989,991.7738259713559,1038.8377042667967,1254.300046999263,452.4252404233362,272.4640668600457,0.0,8.451688131427156,257.1280969062722,835.4243725095461,715.8079186703532,449.81536918460375,200.58077512919888,138.92163592773377,0.0,16544.70932972855,17044.369642254394,1168.4718138583557,1750.5886006464214,10666.464115266075,9632.081790613218,1986.8554928905717],&quot;rowKey&quot;:&quot;Row56&quot;},{&quot;data&quot;:[&quot;2047&quot;,0.0,0.0,4204.021760109659,89715.96060006326,92047.967186119,76939.67663803832,0.0,578.7207708530117,24.447583826612377,614.3222064615358,996.2199921496187,44.16339171623882,2825.139970427624,0.0,0.0,24.121065053321217,702.0280393251685,936.9893925407961,943.6648500759791,1269.957176260325,416.17506236124507,249.72932171276616,0.0,8.49191032036169,251.7476108817459,789.2772295232137,650.229611204391,455.43096021250136,184.50932476777723,127.33026670913196,0.0,16751.2321669574,16102.864723088283,1173.6991950062845,1713.9584408974752,9689.259703802003,8828.387480684743,1827.6469382209082],&quot;rowKey&quot;:&quot;Row57&quot;},{&quot;data&quot;:[&quot;2048&quot;,0.0,0.0,3821.508021729516,84598.3320663696,82922.52965740621,70191.0084193429,0.0,581.0400509532615,23.9316507388592,579.2791357553868,897.4568770678419,44.70513949830651,2577.33097953785,0.0,0.0,24.215155726740566,687.1694984344475,883.5407711013148,850.1118576870479,1285.5265891124875,379.6735857908922,227.00657499483341,0.0,8.528306198259251,246.41895151638144,744.2552296432352,585.7674140769178,461.01511050612896,168.32647818709626,115.74493741086559,0.0,16956.59796987734,15184.3160119125,1178.3949087142653,1677.6810676305904,8728.68733235855,8025.113926977664,1667.3371559873092],&quot;rowKey&quot;:&quot;Row58&quot;},{&quot;data&quot;:[&quot;2049&quot;,0.0,0.0,3439.1994848278955,79610.92862928337,73954.05171458077,63395.57746762272,0.0,583.103339537212,23.42063002293288,545.127835605199,800.3925113206091,45.24384855023742,2327.805947792096,0.0,0.0,24.29855841529575,672.4538693899714,831.4522550509192,758.1680154895379,1301.0084033208318,342.91862190846314,204.29611414034514,0.0,8.560962517073754,241.14155664740613,700.3788396754983,522.4139477872278,466.5678621631667,152.03126515600187,104.16579464991372,0.0,17160.808292028873,14289.141036025223,1182.5713912626336,1641.7526543982817,7784.63702258745,7222.271293533938,1505.9165585076623],&quot;rowKey&quot;:&quot;Row59&quot;},{&quot;data&quot;:[&quot;2050&quot;,0.0,0.0,3057.1045489535154,74755.97597006321,65141.66978424665,56553.10981315832,0.0,584.9166202767813,22.9144738743075,511.88354355671976,705.0175485539601,45.77952290219275,2076.5548260722617,0.0,0.0,24.371525844865886,657.8797527663395,780.7470876923572,667.8244697321766,1316.4027366179055,305.90868314864264,181.59843802255364,0.0,8.589964027288794,235.91492420593858,657.6676419465191,460.1631129772179,472.08925726986956,135.6230263356934,92.59309285344769,0.0,17363.864686523073,13417.739276678018,1186.2407884193692,1606.1697838748091,6857.017872025964,6419.877219289559,1343.3786378274137],&quot;rowKey&quot;:&quot;Row60&quot;}],&quot;fragment&quot;:false,&quot;filtered&quot;:false,&quot;totalRows&quot;:0,&quot;dataHash&quot;:null,&quot;totalFilteredRows&quot;:0,&quot;fragmentFirstRowIndex&quot;:0}"/>
</config>
