<?xml version="1.0" encoding="UTF-8"?>
<config xmlns="http://www.knime.org/2008/09/XMLConfig" xmlns:xsi="http://www.w3.org/2001/XMLSchema-instance" xsi:schemaLocation="http://www.knime.org/2008/09/XMLConfig http://www.knime.org/XMLConfig_2008_09.xsd" key="viewRepresentation">
<entry key="jsCode" type="xstring" value="var body = document.getElementsByTagName(&quot;body&quot;)[0];%%00010var html = '&lt;script src=&quot;https://code.highcharts.com/highcharts.js&quot;&gt;&lt;/script&gt;';%%00010html += '&lt;script src=&quot;https://code.highcharts.com/modules/exporting.js&quot;&gt;&lt;/script&gt;';%%00010html += '&lt;script src=&quot;https://code.highcharts.com/modules/export-data.js&quot;&gt;&lt;/script&gt;';%%00010html += '&lt;div id=&quot;container&quot;&gt;&lt;/div&gt;';%%00010body.innerHTML = html;%%00010%%00010require.config({%%00010    packages: [{%%00010        name: 'highcharts',%%00010        main: 'highcharts'%%00010    }],%%00010    paths: {%%00010        // Change this to your server if you do not wish to use our CDN.%%00010        'highcharts': 'https://code.highcharts.com'%%00010    }%%00010});%%00010%%00010%%00010var data = knimeDataTable.getRows();%%00010// Extract Years column and x values%%00010var x_column_name = &quot;Years&quot;;%%00010var x_column = knimeDataTable.getColumnNames().indexOf(x_column_name);%%00010var x_values = knimeDataTable.getColumn(x_column);%%00010// Create dataset for values%%00010var dataset = [];%%00010%%00010for (var colID = 0; colID &lt; knimeDataTable.getNumColumns(); colID++) {%%00010  var colType = knimeDataTable.getColumnTypes()[colID];%%00010  var colName = knimeDataTable.getColumnNames()[colID];%%00010  //console.log('colomn name',colName)%%00010  if (colType === &quot;number&quot;) {%%00010    dataset.push({%%00010      name: colName,%%00010      //values: data.map(function(d) { // Data%%00010      //       return {x: d.data[x_column], y: d.data[colID]};%%00010      //       })%%00010      data: data.map(function(d) {%%00010        return [parseInt(d.data[x_column]),d.data[colID]];%%00010      })%%00010    });%%00010    console.log(dataset)%%00010  }%%00010}%%00010%%00010var chartData = {%%00010  series: dataset,%%00010  title: &quot;Food intake, Beverages&quot;,%%00010  timeAxis: x_values,%%00010  unit: &quot;t&quot;%%00010};%%00010%%00010//console.log('chartData', chartData)%%00010%%00010require(['highcharts/modules/exporting', 'highcharts/modules/export-data'], function({Highcharts}) {%%00010    %%00010    Highcharts.chart('container', {%%00010    chart: {%%00010      renderTo: ServiceWorkerContainer,%%00010      type: &quot;area&quot;,%%00010      spacingBottom: 30%%00010    },%%00010    title: {%%00010      text: chartData.title%%00010    },%%00010    //subtitle: {%%00010    //    text: 'Source: Wikipedia.org'%%00010    //},%%00010    xAxis: {%%00010        allowDecimals: false,%%00010        labels: {%%00010            formatter: function () {%%00010                return this.value; // clean, unformatted number for year%%00010            }%%00010        }%%00010    },%%00010    yAxis: {%%00010      title: {%%00010        text: chartData.unit%%00010      },%%00010      //labels: {%%00010       // formatter: function() {%%00010       //   return this.value / 1000 + 'k';%%00010       // }%%00010      //}%%00010    },%%00010    tooltip: {%%00010      split: true,%%00010      //pointFormat: '&lt;b&gt;{point.y:,.0f}&lt;/b&gt;&lt;br/&gt; in {point.x}',%%00010      pointFormat: '&lt;span style=&quot;color:{series.color}&quot;&gt;{series.name}&lt;/span&gt;: &lt;b&gt;{point.y:,.0f}&lt;/b&gt; ({point.percentage:.1f}%)&lt;br/&gt;',%%00010      valueDecimals: 2%%00010      //valueSuffix: &quot; millions&quot;%%00010    },%%00010    plotOptions: {%%00010      area: {%%00010        stacking: &quot;normal&quot;,%%00010        lineColor: &quot;#666666&quot;,%%00010        lineWidth: 1,%%00010        marker: {%%00010          lineWidth: 1,%%00010          lineColor: &quot;#666666&quot;,%%00010          enabled:false,%%00010          symbol:'circle',%%00010          radius:2%%00010        }%%00010      }%%00010    },%%00010    responsive: {%%00010      rules: [%%00010        {%%00010          condition: {%%00010            maxWidth: 500%%00010          }%%00010        }%%00010      ]%%00010    },%%00010    series: chartData.series%%00010  });%%00010});%%00010"/>
<entry key="jsSVGCode" type="xstring" value=""/>
<entry key="cssCode" type="xstring" value="body {%%00010    font-family: sans-serif;%%00010}%%00010h1 {%%00010    font-size: 1.5em;%%00010    font-weight: bold;%%00010}%%00010.success {%%00010    color: #006633;%%00010    font-weight: bold;%%00010}%%00010%%00010.failure {%%00010    color: #990000;%%00010    font-weight: bold;%%00010}%%00010%%00010#container {%%00010    min-width: 300px;%%00010    max-width: 1600px;%%00010    height: 500px;%%00010    margin: 1em auto;%%00010}%%00010"/>
<config key="jsDependencies">
<entry key="array-size" type="xint" value="0"/>
</config>
<config key="jsExports">
<entry key="array-size" type="xint" value="0"/>
</config>
<config key="cssDependencies">
<entry key="array-size" type="xint" value="0"/>
</config>
<entry key="knimeDataTableJSON" type="xstring" value="{&quot;@class&quot;:&quot;org.knime.js.core.JSONDataTable&quot;,&quot;id&quot;:&quot;d9a94cb3-a65e-4844-aba6-469207d935c5&quot;,&quot;fragment&quot;:false,&quot;filtered&quot;:false,&quot;rows&quot;:[{&quot;data&quot;:[&quot;1990&quot;,6339174.916660397,180175.89307207867,0.0,656704.4428486857],&quot;rowKey&quot;:&quot;Row0&quot;},{&quot;data&quot;:[&quot;1991&quot;,6125742.849832753,167587.80024898614,0.0,637242.3916784615],&quot;rowKey&quot;:&quot;Row1&quot;},{&quot;data&quot;:[&quot;1992&quot;,5933903.320642878,158614.48992186727,32788.52504844799,655155.7161243015],&quot;rowKey&quot;:&quot;Row2&quot;},{&quot;data&quot;:[&quot;1993&quot;,5753373.633061606,161299.93935547714,0.0,664925.6098781192],&quot;rowKey&quot;:&quot;Row3&quot;},{&quot;data&quot;:[&quot;1994&quot;,5906892.725805446,167926.5233546616,0.0,751445.4364103683],&quot;rowKey&quot;:&quot;Row4&quot;},{&quot;data&quot;:[&quot;1995&quot;,5803693.528600674,145484.9823435007,0.0,650962.6340653795],&quot;rowKey&quot;:&quot;Row5&quot;},{&quot;data&quot;:[&quot;1996&quot;,5947967.347986743,148844.2965235771,0.0,691358.9539082592],&quot;rowKey&quot;:&quot;Row6&quot;},{&quot;data&quot;:[&quot;1997&quot;,5996321.019304281,155367.73504753032,0.0,813444.7279396132],&quot;rowKey&quot;:&quot;Row7&quot;},{&quot;data&quot;:[&quot;1998&quot;,5725612.828346765,145895.42749396295,0.0,834880.8440283996],&quot;rowKey&quot;:&quot;Row8&quot;},{&quot;data&quot;:[&quot;1999&quot;,5831427.308237857,169035.9855512914,0.0,829470.2636717643],&quot;rowKey&quot;:&quot;Row9&quot;},{&quot;data&quot;:[&quot;2000&quot;,5474933.4874821985,145869.3120513148,0.0,898126.1821257467],&quot;rowKey&quot;:&quot;Row10&quot;},{&quot;data&quot;:[&quot;2001&quot;,5703537.377969756,155654.55901714676,0.0,965564.4595941715],&quot;rowKey&quot;:&quot;Row11&quot;},{&quot;data&quot;:[&quot;2002&quot;,5756902.224965406,155546.19473402106,0.0,976025.918521502],&quot;rowKey&quot;:&quot;Row12&quot;},{&quot;data&quot;:[&quot;2003&quot;,5984936.683939523,145756.41029474972,0.0,1046429.0389236776],&quot;rowKey&quot;:&quot;Row13&quot;},{&quot;data&quot;:[&quot;2004&quot;,5910364.253273232,145660.6952889946,0.0,1058923.3537284983],&quot;rowKey&quot;:&quot;Row14&quot;},{&quot;data&quot;:[&quot;2005&quot;,5876510.517095783,146020.29719344326,0.0,1260634.730703926],&quot;rowKey&quot;:&quot;Row15&quot;},{&quot;data&quot;:[&quot;2006&quot;,5580347.571014238,146445.8850913499,46645.72636243003,1131430.0603724297],&quot;rowKey&quot;:&quot;Row16&quot;},{&quot;data&quot;:[&quot;2007&quot;,5430656.6504370775,147100.3799629936,59190.91295083199,1127915.7301186319],&quot;rowKey&quot;:&quot;Row17&quot;},{&quot;data&quot;:[&quot;2008&quot;,5292520.88040991,157833.50227651768,54754.038008848154,1043430.1899095057],&quot;rowKey&quot;:&quot;Row18&quot;},{&quot;data&quot;:[&quot;2009&quot;,4770686.239795862,158671.76482244872,45270.75776007718,1062294.0187265642],&quot;rowKey&quot;:&quot;Row19&quot;},{&quot;data&quot;:[&quot;2010&quot;,4824337.971403456,159369.99351827832,49350.367311057795,1186219.8381190042],&quot;rowKey&quot;:&quot;Row20&quot;},{&quot;data&quot;:[&quot;2011&quot;,4948748.676194574,159644.42148144756,62350.39637258245,1265735.8853364554],&quot;rowKey&quot;:&quot;Row21&quot;},{&quot;data&quot;:[&quot;2012&quot;,4596561.367199424,165034.27642874254,88156.38475900753,1241785.106461737],&quot;rowKey&quot;:&quot;Row22&quot;},{&quot;data&quot;:[&quot;2013&quot;,4445923.420267237,165273.37844893325,117058.98473592056,1187047.6452131665],&quot;rowKey&quot;:&quot;Row23&quot;},{&quot;data&quot;:[&quot;2014&quot;,4716735.697967515,165730.44259612352,102185.15959029684,1295553.1654332834],&quot;rowKey&quot;:&quot;Row24&quot;},{&quot;data&quot;:[&quot;2015&quot;,4940101.968107796,142998.76470192958,102893.29926379546,1341571.896703305],&quot;rowKey&quot;:&quot;Row25&quot;},{&quot;data&quot;:[&quot;2016&quot;,4924538.430115425,119950.52532154584,103600.22872413925,1353531.0675506983],&quot;rowKey&quot;:&quot;Row26&quot;},{&quot;data&quot;:[&quot;2017&quot;,4664933.207105845,136821.10658807447,104298.131780534,1295400.4546919374],&quot;rowKey&quot;:&quot;Row27&quot;},{&quot;data&quot;:[&quot;2018&quot;,4636019.479857198,135968.20547411684,103677.22295158637,1290315.7419367624],&quot;rowKey&quot;:&quot;Row28&quot;},{&quot;data&quot;:[&quot;2019&quot;,4607105.604201357,135115.36107650318,103056.00485300698,1285207.6913879802],&quot;rowKey&quot;:&quot;Row29&quot;},{&quot;data&quot;:[&quot;2020&quot;,4578191.580137179,134262.57338957657,102434.47725367101,1280076.1420024524],&quot;rowKey&quot;:&quot;Row30&quot;},{&quot;data&quot;:[&quot;2021&quot;,4549277.407663516,133409.8424076804,101812.6399222235,1274920.93125191],&quot;rowKey&quot;:&quot;Row31&quot;},{&quot;data&quot;:[&quot;2022&quot;,4520363.08677923,132557.16812515922,101190.49262707905,1269741.895105801],&quot;rowKey&quot;:&quot;Row32&quot;},{&quot;data&quot;:[&quot;2023&quot;,4491448.61748318,131704.55053635823,100568.03513642092,1264538.86801389],&quot;rowKey&quot;:&quot;Row33&quot;},{&quot;data&quot;:[&quot;2024&quot;,4462533.999774223,130851.98963562319,99945.26721820157,1259311.6828886117],&quot;rowKey&quot;:&quot;Row34&quot;},{&quot;data&quot;:[&quot;2025&quot;,4433619.233651216,129999.48541730063,99322.18864014167,1254060.171087202],&quot;rowKey&quot;:&quot;Row35&quot;},{&quot;data&quot;:[&quot;2026&quot;,4404704.319113015,129147.03787573845,98698.79916973019,1248784.1623935392],&quot;rowKey&quot;:&quot;Row36&quot;},{&quot;data&quot;:[&quot;2027&quot;,4375789.256158472,128294.64700528422,98075.0985742239,1243483.4849997726],&quot;rowKey&quot;:&quot;Row37&quot;},{&quot;data&quot;:[&quot;2028&quot;,4346874.044786457,127442.31280028718,97451.08662064743,1238157.9654876585],&quot;rowKey&quot;:&quot;Row38&quot;},{&quot;data&quot;:[&quot;2029&quot;,4317958.684995812,126590.03525509682,96826.76307579252,1232807.4288096572],&quot;rowKey&quot;:&quot;Row39&quot;},{&quot;data&quot;:[&quot;2030&quot;,4289043.176785405,125737.8143640636,96202.12770621812,1227431.6982697486],&quot;rowKey&quot;:&quot;Row40&quot;},{&quot;data&quot;:[&quot;2031&quot;,4260127.520154097,124885.65012153883,95577.18027824971,1222030.5955039824],&quot;rowKey&quot;:&quot;Row41&quot;},{&quot;data&quot;:[&quot;2032&quot;,4231211.715100732,124033.54252187416,94951.9205579794,1216603.9404607536],&quot;rowKey&quot;:&quot;Row42&quot;},{&quot;data&quot;:[&quot;2033&quot;,4202295.761624173,123181.49155942266,94326.34831126565,1211151.5513807873],&quot;rowKey&quot;:&quot;Row43&quot;},{&quot;data&quot;:[&quot;2034&quot;,4173379.659723286,122329.49722853728,93700.46330373238,1205673.2447768573],&quot;rowKey&quot;:&quot;Row44&quot;},{&quot;data&quot;:[&quot;2035&quot;,4144463.409396912,121477.5595235723,93074.26530076942,1200168.8354131873],&quot;rowKey&quot;:&quot;Row45&quot;},{&quot;data&quot;:[&quot;2036&quot;,4115547.0106439176,120625.67843888294,92447.75406753166,1194638.1362845895],&quot;rowKey&quot;:&quot;Row46&quot;},{&quot;data&quot;:[&quot;2037&quot;,4086630.463463165,119773.85396882445,91820.92936893899,1189080.9585952733],&quot;rowKey&quot;:&quot;Row47&quot;},{&quot;data&quot;:[&quot;2038&quot;,4057713.7678535045,118922.08610775357,91193.7909696765,1183497.1117373686],&quot;rowKey&quot;:&quot;Row48&quot;},{&quot;data&quot;:[&quot;2039&quot;,4028796.923813786,118070.37485002728,90566.33863419307,1177886.4032691333],&quot;rowKey&quot;:&quot;Row49&quot;},{&quot;data&quot;:[&quot;2040&quot;,3999879.9313428807,117218.72019000334,89938.5721267019,1172248.6388928434],&quot;rowKey&quot;:&quot;Row50&quot;},{&quot;data&quot;:[&quot;2041&quot;,3970962.7904396392,116367.12212204075,89310.49121118007,1166583.6224323623],&quot;rowKey&quot;:&quot;Row51&quot;},{&quot;data&quot;:[&quot;2042&quot;,3942045.5011029183,115515.5806404989,88682.0956513683,1160891.1558103932],&quot;rowKey&quot;:&quot;Row52&quot;},{&quot;data&quot;:[&quot;2043&quot;,3913128.063331582,114664.09573973765,88053.38521077011,1155171.039025377],&quot;rowKey&quot;:&quot;Row53&quot;},{&quot;data&quot;:[&quot;2044&quot;,3884210.477124472,113812.66741411817,87424.35965265255,1149423.0701280914],&quot;rowKey&quot;:&quot;Row54&quot;},{&quot;data&quot;:[&quot;2045&quot;,3855292.742480461,112961.29565800197,86795.0187400446,1143647.0451978636],&quot;rowKey&quot;:&quot;Row55&quot;},{&quot;data&quot;:[&quot;2046&quot;,3826374.859398398,112109.98046575171,86165.36223573834,1137842.7583184687],&quot;rowKey&quot;:&quot;Row56&quot;},{&quot;data&quot;:[&quot;2047&quot;,3797456.8278771476,111258.72183173023,85535.38990228734,1132010.0015536468],&quot;rowKey&quot;:&quot;Row57&quot;},{&quot;data&quot;:[&quot;2048&quot;,3768538.6479155514,110407.51975030165,84905.10150200706,1126148.5649222867],&quot;rowKey&quot;:&quot;Row58&quot;},{&quot;data&quot;:[&quot;2049&quot;,3739620.3195124823,109556.37421583034,84274.49679697442,1120258.2363732113],&quot;rowKey&quot;:&quot;Row59&quot;},{&quot;data&quot;:[&quot;2050&quot;,3710701.8426667955,108705.28522268211,83643.5755490275,1114338.8017596167],&quot;rowKey&quot;:&quot;Row60&quot;}],&quot;spec&quot;:{&quot;@class&quot;:&quot;org.knime.js.core.JSONDataTableSpec&quot;,&quot;colNames&quot;:[&quot;Years&quot;,&quot;dat_food-intake_beer&quot;,&quot;dat_food-intake_beverages-alcoholic&quot;,&quot;dat_food-intake_beverages-fermented&quot;,&quot;dat_food-intake_wine&quot;],&quot;maxValues&quot;:[&quot;2050&quot;,6339174.916660397,180175.89307207867,117058.98473592056,1353531.0675506983],&quot;hiddenColumns&quot;:[],&quot;filterIds&quot;:[null,null,null,null,null],&quot;numRows&quot;:61,&quot;possibleValues&quot;:[[&quot;1990&quot;,&quot;1991&quot;,&quot;1992&quot;,&quot;1993&quot;,&quot;1994&quot;,&quot;1995&quot;,&quot;1996&quot;,&quot;1997&quot;,&quot;1998&quot;,&quot;1999&quot;,&quot;2000&quot;,&quot;2001&quot;,&quot;2002&quot;,&quot;2003&quot;,&quot;2004&quot;,&quot;2005&quot;,&quot;2006&quot;,&quot;2007&quot;,&quot;2008&quot;,&quot;2009&quot;,&quot;2010&quot;,&quot;2011&quot;,&quot;2012&quot;,&quot;2013&quot;,&quot;2014&quot;,&quot;2015&quot;,&quot;2016&quot;,&quot;2017&quot;,&quot;2018&quot;,&quot;2019&quot;,&quot;2020&quot;,&quot;2021&quot;,&quot;2022&quot;,&quot;2023&quot;,&quot;2024&quot;,&quot;2025&quot;,&quot;2026&quot;,&quot;2027&quot;,&quot;2028&quot;,&quot;2029&quot;,&quot;2030&quot;,&quot;2031&quot;,&quot;2032&quot;,&quot;2033&quot;,&quot;2034&quot;,&quot;2035&quot;,&quot;2036&quot;,&quot;2037&quot;,&quot;2038&quot;,&quot;2039&quot;,&quot;2040&quot;,&quot;2041&quot;,&quot;2042&quot;,&quot;2043&quot;,&quot;2044&quot;,&quot;2045&quot;,&quot;2046&quot;,&quot;2047&quot;,&quot;2048&quot;,&quot;2049&quot;,&quot;2050&quot;],null,null,null,null],&quot;rowColorValues&quot;:[&quot;#404040&quot;,&quot;#404040&quot;,&quot;#404040&quot;,&quot;#404040&quot;,&quot;#404040&quot;,&quot;#404040&quot;,&quot;#404040&quot;,&quot;#404040&quot;,&quot;#404040&quot;,&quot;#404040&quot;,&quot;#404040&quot;,&quot;#404040&quot;,&quot;#404040&quot;,&quot;#404040&quot;,&quot;#404040&quot;,&quot;#404040&quot;,&quot;#404040&quot;,&quot;#404040&quot;,&quot;#404040&quot;,&quot;#404040&quot;,&quot;#404040&quot;,&quot;#404040&quot;,&quot;#404040&quot;,&quot;#404040&quot;,&quot;#404040&quot;,&quot;#404040&quot;,&quot;#404040&quot;,&quot;#404040&quot;,&quot;#404040&quot;,&quot;#404040&quot;,&quot;#404040&quot;,&quot;#404040&quot;,&quot;#404040&quot;,&quot;#404040&quot;,&quot;#404040&quot;,&quot;#404040&quot;,&quot;#404040&quot;,&quot;#404040&quot;,&quot;#404040&quot;,&quot;#404040&quot;,&quot;#404040&quot;,&quot;#404040&quot;,&quot;#404040&quot;,&quot;#404040&quot;,&quot;#404040&quot;,&quot;#404040&quot;,&quot;#404040&quot;,&quot;#404040&quot;,&quot;#404040&quot;,&quot;#404040&quot;,&quot;#404040&quot;,&quot;#404040&quot;,&quot;#404040&quot;,&quot;#404040&quot;,&quot;#404040&quot;,&quot;#404040&quot;,&quot;#404040&quot;,&quot;#404040&quot;,&quot;#404040&quot;,&quot;#404040&quot;,&quot;#404040&quot;],&quot;containsMissingValues&quot;:[false,false,false,false,false],&quot;knimeTypes&quot;:[&quot;String&quot;,&quot;Number (double)&quot;,&quot;Number (double)&quot;,&quot;Number (double)&quot;,&quot;Number (double)&quot;],&quot;colTypes&quot;:[&quot;string&quot;,&quot;number&quot;,&quot;number&quot;,&quot;number&quot;,&quot;number&quot;],&quot;colorModels&quot;:[],&quot;numColumns&quot;:5,&quot;extensionNames&quot;:[],&quot;extensionTypes&quot;:[],&quot;minValues&quot;:[&quot;1990&quot;,3710701.8426667955,108705.28522268211,0.0,637242.3916784615],&quot;rowSizeValues&quot;:null,&quot;numExtensions&quot;:0},&quot;dataHash&quot;:null,&quot;totalFilteredRows&quot;:0,&quot;fragmentFirstRowIndex&quot;:0,&quot;totalRows&quot;:0}"/>
</config>
